dmss_api/__init__.py
dmss_api/api_client.py
dmss_api/configuration.py
dmss_api/exceptions.py
dmss_api/model_utils.py
dmss_api/rest.py
dmss_api/api/__init__.py
dmss_api/api/access_control_api.py
dmss_api/api/attribute_api.py
dmss_api/api/blob_api.py
dmss_api/api/blueprint_api.py
dmss_api/api/datasource_api.py
dmss_api/api/default_api.py
dmss_api/api/document_api.py
dmss_api/api/entity_api.py
dmss_api/api/export_api.py
dmss_api/api/file_api.py
dmss_api/api/health_check_api.py
dmss_api/api/lookup_table_api.py
dmss_api/api/meta_api.py
dmss_api/api/personal_access_token_api.py
dmss_api/api/search_api.py
dmss_api/api/whoami_api.py
dmss_api/apis/__init__.py
dmss_api/model/__init__.py
dmss_api/model/access_control_list.py
dmss_api/model/access_level.py
dmss_api/model/data_source_information.py
dmss_api/model/data_source_request.py
dmss_api/model/dependency.py
dmss_api/model/entity.py
dmss_api/model/error_response.py
dmss_api/model/export_meta_response.py
dmss_api/model/get_blueprint_response.py
dmss_api/model/lookup.py
dmss_api/model/pat_data.py
dmss_api/model/recipe.py
dmss_api/model/recipe_attribute.py
dmss_api/model/repository.py
dmss_api/model/repository_type.py
dmss_api/model/storage_attribute.py
dmss_api/model/storage_data_types.py
dmss_api/model/storage_recipe.py
dmss_api/models/__init__.py
dmss_api-1.4.0.dist-info/METADATA
dmss_api-1.4.0.dist-info/WHEEL
dmss_api-1.4.0.dist-info/top_level.txt
dmss_api-1.4.0.dist-info/RECORD
