Metadata-Version: 2.1
Name: dmss-api
Version: 1.4.0
Summary: Data Modelling Storage Service
Home-page: UNKNOWN
Author: OpenAPI Generator community
Author-email: team@openapitools.org
License: UNKNOWN
Keywords: OpenAPI,OpenAPI-Generator,Data Modelling Storage Service
Platform: UNKNOWN
Requires-Python: >=3.6
Requires-Dist: python-dateutil
Requires-Dist: urllib3 (>=1.25.3)
